vpnc/__init__.py
vpnc-0.2.0.dist-info/LICENSE.txt
vpnc-0.2.0.dist-info/METADATA
vpnc-0.2.0.dist-info/WHEEL
vpnc-0.2.0.dist-info/top_level.txt
vpnc-0.2.0.dist-info/RECORD
