Metadata-Version: 2.1
Name: vpnc
Version: 0.2.0
Summary: Cisco VPN connector
Home-page: https://github.com/tinybike/pyvpnc
Author: Jack Peterson
Author-email: <jack@tinybike.net>
Maintainer: Jack Peterson
Maintainer-email: <jack@tinybike.net>
License: MIT
Download-URL: https://github.com/tinybike/pyvpnc/tarball/0.2.0
Keywords: vpnc,vpn,network,Cisco,concentrator
Platform: UNKNOWN
